kpireport_sql/__init__.py
kpireport_sql/datasource.py
kpireport_sql-0.1.0.dist-info/METADATA
kpireport_sql-0.1.0.dist-info/WHEEL
kpireport_sql-0.1.0.dist-info/entry_points.txt
kpireport_sql-0.1.0.dist-info/top_level.txt
kpireport_sql-0.1.0.dist-info/RECORD
